[

{
    "id":1,
    "name": "UI/UX Designer",
    "address": "Madhya pradesh , INDORE , INDIA",
    "title": " Proficiency in Figma , Adobe XD, Photoshop, Illustrator, or other visual design and wire-framing tools",
    "work": "Exprience : 6 month to 3 Year"
},


{
    "id":2,
    "name": "Web Designer",
    "address": "Madhya pradesh , INDORE , INDIA",
    "work": "Exprience : 6 month to 2 Year"
},


{
    "id":3,
    "name": "Dot Net Developer",
    "address": "Madhya pradesh , INDORE , INDIA",
    "work": " Exprience : 1 to 5 Year"
},


{
    "id":4,
    "name": " MEAN Stack Developer",
    "address": "Madhya pradesh , INDORE , INDIA",
    "work": " Exprience : 1 to 5 Year"
},


{
    "id":5,
    "name": "MERN Stack Developer",
    "address": "Madhya pradesh , INDORE , INDIA",
    "work": " Exprience : 1 to 5 Year"
},


{
    "id":6,
    "name": "Android Develope",
    "address": "Madhya pradesh , INDORE , INDIA",
    "work": " Exprience : 1 to 5 Year"
},


{
    "id":7,
    "name": "IOS Develope",
    "address": "Madhya pradesh , INDORE , INDIA",
    "work": " Exprience : 1 to 5 Year"
},


{
    "id":8,
    "name": "Software Tester",
    "address": "Madhya pradesh , INDORE , INDIA",
    "work": "Exprience : 6 month to 2 Year"
},


{
    "id":9,
    "name": "Digital Marketing Executive",
    "address": "Madhya pradesh , INDORE , INDIA",
    "work": "Exprience : 6 month to 2 Year"
},


{
    "id":10,
    "name": "Talent Acquisition Specialist",
    "address": "Madhya pradesh , INDORE , INDIA",
    "work": "Exprience : 6 month to 2 Year"
},


{
    "id":11,
    "name": "Project Coordinator",
    "address": "Madhya pradesh , INDORE , INDIA",
    "work": "Exprience : 6 month to 2 Year"
},


{
    "id":12,
    "name": "Business Analyst",
    "address": "Madhya pradesh , INDORE , INDIA",
    "work": "Exprience : 6 month to 2 Year"
},



{
    "id":13,
    "name": "UI/UX Designer",
    "address": "Madhya pradesh , INDORE , INDIA",
    "work": "Exprience : 6 month to 3 Year"
},


{
    "id":14,
    "name": "Business Development Executive",
    "address": "Madhya pradesh , INDORE , INDIA",
    "work": "Exprience : 6 month to 2 Year"
},


{
    "id":15,
    "name": "Business Development Manager",
    "address": "Madhya pradesh , INDORE , INDIA",
    "work": "Exprience : 2 to 5 Year"
},


{
    "id":16,
    "name": "Interior Designer",
    "address": "Madhya pradesh , INDORE , INDIA",
    "title": " Proficiency in Figma , Adobe XD, Photoshop, Illustrator, or other visual design and wire-framing tools",
    "work": "Exprience : 6 month to 3 Year"
},


{
    "id":17,
    "name": "PHP Laravel Developer",
    "address": "Madhya pradesh , INDORE , INDIA",
    "work": "Exprience : 6 month to 5 Year"
},



{
    "id":18,
    "name": "Accountant",
    "address": "Madhya pradesh , INDORE , INDIA",
    "work": "Exprience : 6 month to 3 Year"
}





]